[{"total_eth_vol": 1514.0299999999995, "total_sales": 1775}, {"total_eth_vol": 604.2299999999998, "total_sales": 1285}, {"total_eth_vol": 640.9400000000002, "total_sales": 1155}, {"total_eth_vol": 515.6199999999999, "total_sales": 774}, {"total_eth_vol": 320.3000000000003, "total_sales": 1104}, {"total_eth_vol": 446.70000000000016, "total_sales": 822}, {"total_eth_vol": 407.96000000000015, "total_sales": 857}, {"total_eth_vol": 439.39, "total_sales": 835}, {"total_eth_vol": 337.08999999999975, "total_sales": 843}, {"total_eth_vol": 3123.2999999999997, "total_sales": 1038}, {"total_eth_vol": 350.7900000000002, "total_sales": 1038}, {"total_eth_vol": 470.9800000000003, "total_sales": 1084}, {"total_eth_vol": 300.46000000000004, "total_sales": 1136}, {"total_eth_vol": 274.6299999999998, "total_sales": 1184}, {"total_eth_vol": 631.31, "total_sales": 2357}, {"total_eth_vol": 486.8999999999999, "total_sales": 1200}, {"total_eth_vol": 818.3499999999998, "total_sales": 1156}, {"total_eth_vol": 739.41, "total_sales": 926}, {"total_eth_vol": 353.76999999999987, "total_sales": 841}, {"total_eth_vol": 395.70999999999987, "total_sales": 659}, {"total_eth_vol": 636.6300000000001, "total_sales": 1074}, {"total_eth_vol": 425.31000000000006, "total_sales": 846}, {"total_eth_vol": 383.04, "total_sales": 671}, {"total_eth_vol": 1259.5600000000004, "total_sales": 817}]