[{"total_eth_vol": 4822.199999999999, "total_sales": 523}, {"total_eth_vol": 417.22000000000014, "total_sales": 744}, {"total_eth_vol": 97205.89999999998, "total_sales": 589}, {"total_eth_vol": 234.26000000000005, "total_sales": 562}, {"total_eth_vol": 4472.050000000001, "total_sales": 352}, {"total_eth_vol": 5641.620000000001, "total_sales": 494}, {"total_eth_vol": 451.79000000000013, "total_sales": 513}, {"total_eth_vol": 498.8300000000003, "total_sales": 745}, {"total_eth_vol": 456.05, "total_sales": 1294}, {"total_eth_vol": 528.1, "total_sales": 696}, {"total_eth_vol": 534.2899999999996, "total_sales": 834}, {"total_eth_vol": 334.08000000000027, "total_sales": 807}, {"total_eth_vol": 824.0600000000005, "total_sales": 741}, {"total_eth_vol": 691.76, "total_sales": 806}, {"total_eth_vol": 632.2, "total_sales": 698}, {"total_eth_vol": 593.4799999999998, "total_sales": 931}, {"total_eth_vol": 555.2499999999998, "total_sales": 931}, {"total_eth_vol": 6839.66, "total_sales": 651}, {"total_eth_vol": 425.22000000000014, "total_sales": 623}, {"total_eth_vol": 786.9600000000005, "total_sales": 570}, {"total_eth_vol": 776.4600000000005, "total_sales": 684}, {"total_eth_vol": 1150.6299999999997, "total_sales": 856}, {"total_eth_vol": 1427.8, "total_sales": 1010}, {"total_eth_vol": 4590.989999999998, "total_sales": 816}]