[{"Collection name": "Ringers by Dmitri Cherniak", "volume": 22.5, "coin": "ETH", "Sold Amount": 1}, {"Collection name": "PROOF Collective", "volume": 9.2, "coin": "ETH", "Sold Amount": 1}, {"Collection name": "y00ts", "volume": 5.9, "coin": "ETH", "Sold Amount": 3}, {"Collection name": "Moonbirds", "volume": 5.2, "coin": "ETH", "Sold Amount": 2}, {"Collection name": "Meebits", "volume": 4.5, "coin": "ETH", "Sold Amount": 2}, {"Collection name": "Trump Digital Trading Cards Series 2", "volume": 4.3, "coin": "ETH", "Sold Amount": 70}, {"Collection name": "Opepen Edition", "volume": 3.1, "coin": "ETH", "Sold Amount": 9}, {"Collection name": "Nakamigos", "volume": 4.5, "coin": "ETH", "Sold Amount": 13}, {"Collection name": "Otherside Vessels", "volume": 4.8, "coin": "ETH", "Sold Amount": 10}, {"Collection name": "Redacted Remilio Babies", "volume": 5.5, "coin": "ETH", "Sold Amount": 6}, {"Collection name": "AIShiba OG Collection", "volume": 8.9, "coin": "ETH", "Sold Amount": 328}, {"Collection name": "Otherdeed Expanded", "volume": 6.9, "coin": "ETH", "Sold Amount": 6}, {"Collection name": "Seizon", "volume": 9.1, "coin": "ETH", "Sold Amount": 124}, {"Collection name": "Milady Maker", "volume": 11.7, "coin": "ETH", "Sold Amount": 5}, {"Collection name": "Otherdeed for Otherside", "volume": 10.0, "coin": "ETH", "Sold Amount": 8}, {"Collection name": "Cool Cats NFT", "volume": 9.8, "coin": "ETH", "Sold Amount": 12}, {"Collection name": "Consortium Key", "volume": 11.5, "coin": "ETH", "Sold Amount": 3}, {"Collection name": "The Captainz", "volume": 14.3, "coin": "ETH", "Sold Amount": 2}, {"Collection name": "BEANZ Official", "volume": 13.7, "coin": "ETH", "Sold Amount": 9}, {"Collection name": "Bored Ape Kennel Club", "volume": 14.6, "coin": "ETH", "Sold Amount": 3}, {"Collection name": "CLONE X - X TAKASHI MURAKAMI", "volume": 51.4, "coin": "ETH", "Sold Amount": 20}, {"Collection name": "Otherside Koda", "volume": 29.4, "coin": "ETH", "Sold Amount": 3}, {"Collection name": "DeGods", "volume": 24.5, "coin": "ETH", "Sold Amount": 3}, {"Collection name": "Azuki", "volume": 30.8, "coin": "ETH", "Sold Amount": 2}, {"Collection name": "Mutant Ape Yacht Club", "volume": 228.5, "coin": "ETH", "Sold Amount": 20}, {"Collection name": "DEGEN TOONZ COLLECTION", "volume": 55.6, "coin": "ETH", "Sold Amount": 3}, {"Collection name": "Wrapped Cryptopunks", "volume": 300.8, "coin": "ETH", "Sold Amount": 6}, {"Collection name": "HV-MTL", "volume": 3.1, "coin": "ETH", "Sold Amount": 2}, {"Collection name": "RTFKT Animus Egg \ud83e\udd5a", "volume": 3.0, "coin": "ETH", "Sold Amount": 6}, {"Collection name": "FoxFam", "volume": 2.4, "coin": "ETH", "Sold Amount": 39}, {"Collection name": "Decoherence by Van Arman", "volume": 2.3, "coin": "ETH", "Sold Amount": 1}, {"Collection name": "Sappy Seals", "volume": 2.3, "coin": "ETH", "Sold Amount": 4}, {"Collection name": "Doodles", "volume": 2.3, "coin": "ETH", "Sold Amount": 1}, {"Collection name": "Damien Hirst - The Currency", "volume": 2.4, "coin": "ETH", "Sold Amount": 1}, {"Collection name": "The Potatoz", "volume": 3.0, "coin": "ETH", "Sold Amount": 1}, {"Collection name": "MurMur Cats", "volume": 2.2, "coin": "ETH", "Sold Amount": 1}, {"Collection name": "My Pet Hooligan", "volume": 1.9, "coin": "ETH", "Sold Amount": 3}, {"Collection name": "RENGA", "volume": 1.7, "coin": "ETH", "Sold Amount": 3}, {"Collection name": "Checks - VV Edition", "volume": 1.6, "coin": "ETH", "Sold Amount": 4}, {"Collection name": "Mirandus", "volume": 1.5, "coin": "ETH", "Sold Amount": 1}, {"Collection name": "Trump Digital Trading Cards", "volume": 1.8, "coin": "ETH", "Sold Amount": 13}, {"Collection name": "11 Captain's Club (Official)", "volume": 2.0, "coin": "ETH", "Sold Amount": 1}, {"Collection name": "rektguy", "volume": 1.9, "coin": "ETH", "Sold Amount": 3}, {"Collection name": "ArcadeNFT", "volume": 2.2, "coin": "ETH", "Sold Amount": 2}, {"Collection name": "CyberKongz (Babies)", "volume": 1.2, "coin": "ETH", "Sold Amount": 1}, {"Collection name": "OCM Dessert", "volume": 1.2, "coin": "ETH", "Sold Amount": 1}, {"Collection name": "Genuine Undead", "volume": 1.1, "coin": "ETH", "Sold Amount": 5}, {"Collection name": "LoudPunx", "volume": 1.1, "coin": "ETH", "Sold Amount": 1}, {"Collection name": "Murakami.Flowers Official", "volume": 1.2, "coin": "ETH", "Sold Amount": 2}, {"Collection name": "Invisible Friends", "volume": 1.4, "coin": "ETH", "Sold Amount": 1}, {"Collection name": "Cat & Mouse", "volume": 1.2, "coin": "ETH", "Sold Amount": 125}, {"Collection name": "Elemental by Fang Lijun", "volume": 1.4, "coin": "ETH", "Sold Amount": 2}, {"Collection name": "Gemesis", "volume": 0.86, "coin": "ETH", "Sold Amount": 31}, {"Collection name": "DenDekaDen Genesis Omikuji", "volume": 0.82, "coin": "ETH", "Sold Amount": 2}, {"Collection name": "Diamond Exhibition: Day One Pass", "volume": 0.76, "coin": "ETH", "Sold Amount": 3}, {"Collection name": "FEWOCiOUS x FewoWorld: Paint", "volume": 0.76, "coin": "ETH", "Sold Amount": 2}, {"Collection name": "Valeria Games Genesis Land", "volume": 0.79, "coin": "ETH", "Sold Amount": 4}, {"Collection name": "Cool Cats: Fractures", "volume": 0.85, "coin": "ETH", "Sold Amount": 2}, {"Collection name": "CyberBrokers", "volume": 0.91, "coin": "ETH", "Sold Amount": 2}, {"Collection name": "Ignition by ge1doot", "volume": 0.89, "coin": "ETH", "Sold Amount": 1}, {"Collection name": "RENGA Black Box", "volume": 0.91, "coin": "ETH", "Sold Amount": 1}, {"Collection name": "TPL Mech Afterglow", "volume": 0.74, "coin": "ETH", "Sold Amount": 5}, {"Collection name": "VeeFriends Series 2", "volume": 0.71, "coin": "ETH", "Sold Amount": 5}, {"Collection name": "Genesis Dimensional Stones", "volume": 0.71, "coin": "ETH", "Sold Amount": 1}, {"Collection name": "The Blitnauts", "volume": 0.71, "coin": "ETH", "Sold Amount": 1}, {"Collection name": "Lens Protocol Profiles", "volume": 0.71, "coin": "ETH", "Sold Amount": 7}, {"Collection name": "ArcheWorld_Land(POLYGON)", "volume": 0.72, "coin": "ETH", "Sold Amount": 2}, {"Collection name": "Ultiverse - Electric Sheep", "volume": 0.75, "coin": "ETH", "Sold Amount": 1}, {"Collection name": "Underground Pass", "volume": 0.74, "coin": "ETH", "Sold Amount": 1}, {"Collection name": "The Sandbox", "volume": 0.67, "coin": "ETH", "Sold Amount": 1}, {"Collection name": "LuppyclubOfficial", "volume": 0.66, "coin": "ETH", "Sold Amount": 1}, {"Collection name": "Wolf Game - Farmer", "volume": 0.58, "coin": "ETH", "Sold Amount": 4}, {"Collection name": "YON EDITIONS", "volume": 0.57, "coin": "ETH", "Sold Amount": 11}, {"Collection name": "OmniBTC", "volume": 3.3, "coin": "BNB", "Sold Amount": 28}, {"Collection name": "The Memes by 6529", "volume": 0.65, "coin": "ETH", "Sold Amount": 3}, {"Collection name": "0N1 Force", "volume": 0.66, "coin": "ETH", "Sold Amount": 1}, {"Collection name": "Mocaverse", "volume": 0.7, "coin": "ETH", "Sold Amount": 1}, {"Collection name": "DigiDaigaku Super Villains", "volume": 0.68, "coin": "ETH", "Sold Amount": 2}, {"Collection name": "Outlaws", "volume": 0.55, "coin": "ETH", "Sold Amount": 13}, {"Collection name": "Deadfellaz", "volume": 0.5, "coin": "ETH", "Sold Amount": 2}, {"Collection name": "GMX Blueberry Club", "volume": 0.45, "coin": "ETH", "Sold Amount": 1}, {"Collection name": "Drill Club", "volume": 0.44, "coin": "ETH", "Sold Amount": 22}, {"Collection name": "a KID called BEAST", "volume": 0.44, "coin": "ETH", "Sold Amount": 1}, {"Collection name": "VLVT Origins", "volume": 0.5, "coin": "ETH", "Sold Amount": 1}, {"Collection name": "Valhalla", "volume": 0.54, "coin": "ETH", "Sold Amount": 1}, {"Collection name": "CREYZIES", "volume": 0.55, "coin": "ETH", "Sold Amount": 1}, {"Collection name": "Ravendale", "volume": 0.43, "coin": "ETH", "Sold Amount": 1}, {"Collection name": "Future Realities: Sys32Template x Reddit Collectible Avatars", "volume": 0.43, "coin": "ETH", "Sold Amount": 2}, {"Collection name": "Cryptoon Goonz", "volume": 0.42, "coin": "ETH", "Sold Amount": 2}, {"Collection name": "Llamaverse Genesis", "volume": 0.41, "coin": "ETH", "Sold Amount": 1}, {"Collection name": "Degen2009", "volume": 0.4, "coin": "ETH", "Sold Amount": 1}, {"Collection name": "Cheers UP Official", "volume": 0.41, "coin": "ETH", "Sold Amount": 2}, {"Collection name": "Dream Capsules by Obvious", "volume": 0.42, "coin": "ETH", "Sold Amount": 3}, {"Collection name": "Exosama", "volume": 0.43, "coin": "ETH", "Sold Amount": 2}, {"Collection name": "Muppeth", "volume": 0.43, "coin": "ETH", "Sold Amount": 10}, {"Collection name": "Saved Souls", "volume": 0.39, "coin": "ETH", "Sold Amount": 4}, {"Collection name": "YuliOriginGenOne", "volume": 2.3, "coin": "BNB", "Sold Amount": 3}, {"Collection name": "Checks - VV Originals", "volume": 0.38, "coin": "ETH", "Sold Amount": 1}, {"Collection name": "Otherside Relics", "volume": 0.36, "coin": "ETH", "Sold Amount": 1}, {"Collection name": "Mythics Eggs", "volume": 0.39, "coin": "ETH", "Sold Amount": 1}]