[{"Collection name": "CLONE X - X TAKASHI MURAKAMI", "volume": 19.5, "coin": "ETH", "Sold Amount": 5}, {"Collection name": "AIShiba OG Collection", "volume": 9.8, "coin": "ETH", "Sold Amount": 845}, {"Collection name": "FLUF World", "volume": 7.1, "coin": "ETH", "Sold Amount": 4}, {"Collection name": "Trump Digital Trading Cards", "volume": 6.1, "coin": "ETH", "Sold Amount": 36}, {"Collection name": "OnChainMonkey", "volume": 5.0, "coin": "ETH", "Sold Amount": 1}, {"Collection name": "Meebits", "volume": 4.5, "coin": "ETH", "Sold Amount": 2}, {"Collection name": "QQL", "volume": 4.5, "coin": "ETH", "Sold Amount": 1}, {"Collection name": "Milady Maker", "volume": 4.8, "coin": "ETH", "Sold Amount": 2}, {"Collection name": "Otherdeed for Otherside", "volume": 5.3, "coin": "ETH", "Sold Amount": 2}, {"Collection name": "The Captainz", "volume": 6.7, "coin": "ETH", "Sold Amount": 1}, {"Collection name": "Pudgy Penguins", "volume": 7.3, "coin": "ETH", "Sold Amount": 2}, {"Collection name": "Opepen Edition", "volume": 7.1, "coin": "ETH", "Sold Amount": 19}, {"Collection name": "DeGods", "volume": 7.5, "coin": "ETH", "Sold Amount": 1}, {"Collection name": "Terraforms by Mathcastles", "volume": 11.7, "coin": "ETH", "Sold Amount": 7}, {"Collection name": "Two Bit Bears", "volume": 10.3, "coin": "ETH", "Sold Amount": 128}, {"Collection name": "WonderPals", "volume": 9.9, "coin": "ETH", "Sold Amount": 87}, {"Collection name": "y00ts", "volume": 10.4, "coin": "ETH", "Sold Amount": 6}, {"Collection name": "Bored Ape Kennel Club", "volume": 15.3, "coin": "ETH", "Sold Amount": 3}, {"Collection name": "Moonbirds", "volume": 11.7, "coin": "ETH", "Sold Amount": 4}, {"Collection name": "Parallel Alpha", "volume": 15.8, "coin": "ETH", "Sold Amount": 3}, {"Collection name": "FaceLessssssssssss", "volume": 28.0, "coin": "ETH", "Sold Amount": 1}, {"Collection name": "BEANZ Official", "volume": 20.9, "coin": "ETH", "Sold Amount": 13}, {"Collection name": "Nakamigos", "volume": 20.7, "coin": "ETH", "Sold Amount": 56}, {"Collection name": "World of Women", "volume": 21.0, "coin": "ETH", "Sold Amount": 22}, {"Collection name": "Azuki", "volume": 70.5, "coin": "ETH", "Sold Amount": 4}, {"Collection name": "Trump Digital Trading Cards Series 2", "volume": 31.9, "coin": "ETH", "Sold Amount": 350}, {"Collection name": "Mutant Ape Yacht Club", "volume": 343.2, "coin": "ETH", "Sold Amount": 29}, {"Collection name": "NEOSTACKEY", "volume": 4.3, "coin": "ETH", "Sold Amount": 6}, {"Collection name": "Inhabitants: Generative Identities", "volume": 3.9, "coin": "ETH", "Sold Amount": 5}, {"Collection name": "Checks - VV Originals", "volume": 3.6, "coin": "ETH", "Sold Amount": 11}, {"Collection name": "HV-MTL", "volume": 3.3, "coin": "ETH", "Sold Amount": 2}, {"Collection name": "Saved Souls", "volume": 3.3, "coin": "ETH", "Sold Amount": 52}, {"Collection name": "CryptoDickbutts", "volume": 3.4, "coin": "ETH", "Sold Amount": 3}, {"Collection name": "Redacted Remilio Babies", "volume": 3.6, "coin": "ETH", "Sold Amount": 6}, {"Collection name": "NFT Worlds", "volume": 4.0, "coin": "ETH", "Sold Amount": 2}, {"Collection name": "World of Women Galaxy", "volume": 3.2, "coin": "ETH", "Sold Amount": 40}, {"Collection name": "Consortium Key", "volume": 3.0, "coin": "ETH", "Sold Amount": 1}, {"Collection name": "LuppyclubOfficial", "volume": 2.9, "coin": "ETH", "Sold Amount": 1}, {"Collection name": "Cool Cats NFT", "volume": 2.8, "coin": "ETH", "Sold Amount": 3}, {"Collection name": "Steady Stack Titans Official", "volume": 2.4, "coin": "ETH", "Sold Amount": 1}, {"Collection name": "The Potatoz", "volume": 3.0, "coin": "ETH", "Sold Amount": 1}, {"Collection name": "Checks - VV Edition", "volume": 3.2, "coin": "ETH", "Sold Amount": 7}, {"Collection name": "RENGA", "volume": 3.0, "coin": "ETH", "Sold Amount": 5}, {"Collection name": "Gemesis", "volume": 3.2, "coin": "ETH", "Sold Amount": 62}, {"Collection name": "Smol Brains", "volume": 2.2, "coin": "ETH", "Sold Amount": 1}, {"Collection name": "a KID called BEAST", "volume": 1.8, "coin": "ETH", "Sold Amount": 3}, {"Collection name": "Bulls and Apes Project - Genesis", "volume": 1.6, "coin": "ETH", "Sold Amount": 1}, {"Collection name": "Genesis Dimensional Stones", "volume": 1.5, "coin": "ETH", "Sold Amount": 2}, {"Collection name": "Bit Bears by Berachain", "volume": 1.8, "coin": "ETH", "Sold Amount": 1}, {"Collection name": "CyberKongz VX", "volume": 2.3, "coin": "ETH", "Sold Amount": 8}, {"Collection name": "Wumbo Pass", "volume": 2.2, "coin": "ETH", "Sold Amount": 1}, {"Collection name": "Doodles", "volume": 2.4, "coin": "ETH", "Sold Amount": 1}, {"Collection name": "SchizoPosters", "volume": 1.4, "coin": "ETH", "Sold Amount": 5}, {"Collection name": "0N1 Force", "volume": 1.3, "coin": "ETH", "Sold Amount": 2}, {"Collection name": "ENS: Ethereum Name Service", "volume": 1.3, "coin": "ETH", "Sold Amount": 3}, {"Collection name": "BROZO", "volume": 1.2, "coin": "ETH", "Sold Amount": 47}, {"Collection name": "Genuine Undead", "volume": 1.3, "coin": "ETH", "Sold Amount": 6}, {"Collection name": "CyberBrokers", "volume": 1.4, "coin": "ETH", "Sold Amount": 3}, {"Collection name": "Otherside Vessels", "volume": 1.4, "coin": "ETH", "Sold Amount": 3}, {"Collection name": "Pepe Open Editions by Matt Furie", "volume": 1.4, "coin": "ETH", "Sold Amount": 53}, {"Collection name": "Chimpers", "volume": 1.5, "coin": "ETH", "Sold Amount": 1}, {"Collection name": "Hashmasks", "volume": 1.0, "coin": "ETH", "Sold Amount": 4}, {"Collection name": "The Memes by 6529", "volume": 0.97, "coin": "ETH", "Sold Amount": 4}, {"Collection name": "Mint Pass Tokyo AI Collection | Bright Moments | MPAI", "volume": 0.95, "coin": "ETH", "Sold Amount": 1}, {"Collection name": "lobsterdao", "volume": 0.95, "coin": "ETH", "Sold Amount": 1}, {"Collection name": "Crypto Unicorns Land Market", "volume": 0.96, "coin": "ETH", "Sold Amount": 32}, {"Collection name": "Outlaws", "volume": 1.0, "coin": "ETH", "Sold Amount": 18}, {"Collection name": "ALTS by adidas", "volume": 1.2, "coin": "ETH", "Sold Amount": 3}, {"Collection name": "Defybirds", "volume": 1.1, "coin": "ETH", "Sold Amount": 1}, {"Collection name": "Lazy Lions", "volume": 0.89, "coin": "ETH", "Sold Amount": 4}, {"Collection name": "Loot (for Adventurers)", "volume": 0.85, "coin": "ETH", "Sold Amount": 2}, {"Collection name": "Otherdeed Expanded", "volume": 0.84, "coin": "ETH", "Sold Amount": 1}, {"Collection name": "10KTF Stockroom", "volume": 0.84, "coin": "ETH", "Sold Amount": 2}, {"Collection name": "Algoritmo Divino", "volume": 0.8, "coin": "ETH", "Sold Amount": 3}, {"Collection name": "Pixelmon - Generation 1", "volume": 0.85, "coin": "ETH", "Sold Amount": 1}, {"Collection name": "Umuco's ART", "volume": 0.85, "coin": "ETH", "Sold Amount": 3}, {"Collection name": "Bridgeworld Legions", "volume": 0.94, "coin": "ETH", "Sold Amount": 7}, {"Collection name": "Kubz", "volume": 0.93, "coin": "ETH", "Sold Amount": 1}, {"Collection name": "Primapes", "volume": 0.79, "coin": "ETH", "Sold Amount": 1}, {"Collection name": "Mythics Eggs", "volume": 0.76, "coin": "ETH", "Sold Amount": 2}, {"Collection name": "Otherside Relics", "volume": 0.73, "coin": "ETH", "Sold Amount": 2}, {"Collection name": "CrypToadz by GREMPLIN", "volume": 0.71, "coin": "ETH", "Sold Amount": 1}, {"Collection name": "Pixelmon Trainers - Generation 1", "volume": 0.69, "coin": "ETH", "Sold Amount": 2}, {"Collection name": "The Bakery Genesis", "volume": 0.76, "coin": "ETH", "Sold Amount": 2}, {"Collection name": "Everai Heroes: Duo", "volume": 0.77, "coin": "ETH", "Sold Amount": 6}, {"Collection name": "alien frens", "volume": 0.79, "coin": "ETH", "Sold Amount": 4}, {"Collection name": "Friendship Bracelets by Alexis Andr\u00e9", "volume": 0.66, "coin": "ETH", "Sold Amount": 4}, {"Collection name": "Mocaverse", "volume": 0.65, "coin": "ETH", "Sold Amount": 1}, {"Collection name": "Wolf Game", "volume": 0.63, "coin": "ETH", "Sold Amount": 3}, {"Collection name": "montreal friend scale by amon tobin", "volume": 0.6, "coin": "ETH", "Sold Amount": 3}, {"Collection name": "Cool Cats: Fractures", "volume": 0.59, "coin": "ETH", "Sold Amount": 4}, {"Collection name": "colR Digital Founders Club", "volume": 0.6, "coin": "ETH", "Sold Amount": 1}, {"Collection name": "AlphaSharks NFT", "volume": 0.63, "coin": "ETH", "Sold Amount": 4}, {"Collection name": "rektguy", "volume": 0.65, "coin": "ETH", "Sold Amount": 1}, {"Collection name": "Pepedenza Editions by Batz", "volume": 0.66, "coin": "ETH", "Sold Amount": 2}, {"Collection name": "Genesis Box", "volume": 0.59, "coin": "ETH", "Sold Amount": 8}, {"Collection name": "PartyBear", "volume": 0.57, "coin": "ETH", "Sold Amount": 2}, {"Collection name": "Seizon", "volume": 0.57, "coin": "ETH", "Sold Amount": 5}, {"Collection name": "Pome Survival Companion Pet", "volume": 3.4, "coin": "BNB", "Sold Amount": 24}, {"Collection name": "Iron Paw Gang", "volume": 0.57, "coin": "ETH", "Sold Amount": 3}]