[{"Collection name": "DeGods", "volume": 8.4, "coin": "ETH", "Sold Amount": 1}, {"Collection name": "HV-MTL", "volume": 3.8, "coin": "ETH", "Sold Amount": 3}, {"Collection name": "Emblem Vault Legacy", "volume": 3.0, "coin": "ETH", "Sold Amount": 7}, {"Collection name": "Otherside Vessels", "volume": 2.4, "coin": "ETH", "Sold Amount": 5}, {"Collection name": "Pudgy Rods", "volume": 2.1, "coin": "ETH", "Sold Amount": 7}, {"Collection name": "IO: Imaginary Ones", "volume": 2.1, "coin": "ETH", "Sold Amount": 3}, {"Collection name": "XCOPY", "volume": 2.8, "coin": "ETH", "Sold Amount": 1}, {"Collection name": "DigiDaigaku Genesis", "volume": 3.1, "coin": "ETH", "Sold Amount": 1}, {"Collection name": "Opepen Edition", "volume": 3.1, "coin": "ETH", "Sold Amount": 11}, {"Collection name": "Terraforms by Mathcastles", "volume": 3.1, "coin": "ETH", "Sold Amount": 3}, {"Collection name": "Redacted Remilio Babies", "volume": 4.5, "coin": "ETH", "Sold Amount": 3}, {"Collection name": "Bored Ape Kennel Club", "volume": 4.0, "coin": "ETH", "Sold Amount": 1}, {"Collection name": "Milady Maker", "volume": 5.1, "coin": "ETH", "Sold Amount": 1}, {"Collection name": "Otherdeed for Otherside", "volume": 20.5, "coin": "ETH", "Sold Amount": 5}, {"Collection name": "Fancy Nouns", "volume": 11.7, "coin": "ETH", "Sold Amount": 29}, {"Collection name": "The Captainz", "volume": 9.0, "coin": "ETH", "Sold Amount": 1}, {"Collection name": "Azuki", "volume": 14.1, "coin": "ETH", "Sold Amount": 1}, {"Collection name": "Mutant Ape Yacht Club", "volume": 30.4, "coin": "ETH", "Sold Amount": 3}, {"Collection name": "CLONE X - X TAKASHI MURAKAMI", "volume": 30.1, "coin": "ETH", "Sold Amount": 11}, {"Collection name": "Pixelady Maker", "volume": 31.5, "coin": "ETH", "Sold Amount": 117}]