[{"Collection name": "HV-MTL", "volume": 10.7, "coin": "ETH", "Sold Amount": 8}, {"Collection name": "Rumble Kong League", "volume": 6.6, "coin": "ETH", "Sold Amount": 18}, {"Collection name": "Otherdeed Expanded", "volume": 3.1, "coin": "ETH", "Sold Amount": 1}, {"Collection name": "Saved Souls", "volume": 3.0, "coin": "ETH", "Sold Amount": 37}, {"Collection name": "My Pet Hooligan", "volume": 2.8, "coin": "ETH", "Sold Amount": 4}, {"Collection name": "Limited Designer Editions", "volume": 2.8, "coin": "ETH", "Sold Amount": 5}, {"Collection name": "CLONE X - X TAKASHI MURAKAMI", "volume": 3.0, "coin": "ETH", "Sold Amount": 1}, {"Collection name": "Checks - VV Elements", "volume": 5.0, "coin": "ETH", "Sold Amount": 1}, {"Collection name": "Redacted Remilio Babies", "volume": 4.0, "coin": "ETH", "Sold Amount": 4}, {"Collection name": "Otherdeed for Otherside", "volume": 5.1, "coin": "ETH", "Sold Amount": 5}, {"Collection name": "KILLABEARS", "volume": 7.0, "coin": "ETH", "Sold Amount": 1}, {"Collection name": "Checks - VV Originals", "volume": 6.6, "coin": "ETH", "Sold Amount": 9}, {"Collection name": "Checks - VV Edition", "volume": 10.3, "coin": "ETH", "Sold Amount": 13}, {"Collection name": "Nakamigos", "volume": 28.7, "coin": "ETH", "Sold Amount": 86}, {"Collection name": "BEANZ Official", "volume": 22.2, "coin": "ETH", "Sold Amount": 16}, {"Collection name": "Mutant Ape Yacht Club", "volume": 19.7, "coin": "ETH", "Sold Amount": 2}, {"Collection name": "mfers", "volume": 24.8, "coin": "ETH", "Sold Amount": 27}, {"Collection name": "Pudgy Penguins", "volume": 93.4, "coin": "ETH", "Sold Amount": 18}, {"Collection name": "Milady Maker", "volume": 31.5, "coin": "ETH", "Sold Amount": 10}, {"Collection name": "Opepen Edition", "volume": 273.9, "coin": "ETH", "Sold Amount": 254}]