[{"Collection name": "CryptoPunks V1 (wrapped)", "volume": 30.9, "coin": "ETH", "Sold Amount": 7}, {"Collection name": "HV-MTL", "volume": 7.2, "coin": "ETH", "Sold Amount": 4}, {"Collection name": "Valhalla", "volume": 5.7, "coin": "ETH", "Sold Amount": 9}, {"Collection name": "Doodles", "volume": 5.5, "coin": "ETH", "Sold Amount": 2}, {"Collection name": "Gemesis", "volume": 5.1, "coin": "ETH", "Sold Amount": 102}, {"Collection name": "Kanpai Pandas", "volume": 4.7, "coin": "ETH", "Sold Amount": 3}, {"Collection name": "Ordinal Kubz", "volume": 4.6, "coin": "ETH", "Sold Amount": 15}, {"Collection name": "Kandyland", "volume": 4.7, "coin": "ETH", "Sold Amount": 58}, {"Collection name": "XCOPY", "volume": 5.3, "coin": "ETH", "Sold Amount": 1}, {"Collection name": "REWORLD by Roope Rainisto", "volume": 5.5, "coin": "ETH", "Sold Amount": 4}, {"Collection name": "Nakamapes", "volume": 6.0, "coin": "ETH", "Sold Amount": 239}, {"Collection name": "Otherdeed Expanded", "volume": 5.7, "coin": "ETH", "Sold Amount": 6}, {"Collection name": "Opepen Edition", "volume": 6.7, "coin": "ETH", "Sold Amount": 14}, {"Collection name": "RENGA", "volume": 9.5, "coin": "ETH", "Sold Amount": 13}, {"Collection name": "Redacted Remilio Babies", "volume": 7.8, "coin": "ETH", "Sold Amount": 14}, {"Collection name": "Otherside Relics", "volume": 7.4, "coin": "ETH", "Sold Amount": 12}, {"Collection name": "y00ts", "volume": 8.1, "coin": "ETH", "Sold Amount": 4}, {"Collection name": "Otherdeed for Otherside", "volume": 14.0, "coin": "ETH", "Sold Amount": 8}, {"Collection name": "Pixelmon - Generation 1", "volume": 11.5, "coin": "ETH", "Sold Amount": 20}, {"Collection name": "Nakamigos", "volume": 27.1, "coin": "ETH", "Sold Amount": 30}, {"Collection name": "The Bibiz", "volume": 59.8, "coin": "ETH", "Sold Amount": 2}, {"Collection name": "The Captainz", "volume": 36.6, "coin": "ETH", "Sold Amount": 6}, {"Collection name": "Azuki", "volume": 32.0, "coin": "ETH", "Sold Amount": 2}, {"Collection name": "XXD34D", "volume": 44.5, "coin": "ETH", "Sold Amount": 512}, {"Collection name": "Bored Ape Yacht Club", "volume": 131.6, "coin": "ETH", "Sold Amount": 2}, {"Collection name": "ETHEREALS WTF", "volume": 67.8, "coin": "ETH", "Sold Amount": 3}, {"Collection name": "Mutant Ape Yacht Club", "volume": 142.3, "coin": "ETH", "Sold Amount": 11}, {"Collection name": "Otherside Vessels", "volume": 4.6, "coin": "ETH", "Sold Amount": 12}, {"Collection name": "OnChainMonkey", "volume": 3.8, "coin": "ETH", "Sold Amount": 2}, {"Collection name": "Owlpha", "volume": 3.2, "coin": "ETH", "Sold Amount": 24}, {"Collection name": "NFTiff", "volume": 3.0, "coin": "ETH", "Sold Amount": 1}, {"Collection name": "Checks - VV Edition", "volume": 2.9, "coin": "ETH", "Sold Amount": 4}, {"Collection name": "Moonbirds", "volume": 3.1, "coin": "ETH", "Sold Amount": 1}, {"Collection name": "OVERWORLD - GENESIS KEYS", "volume": 3.6, "coin": "ETH", "Sold Amount": 9}, {"Collection name": "Exchange Pass", "volume": 3.9, "coin": "ETH", "Sold Amount": 9}, {"Collection name": "Milady Maker", "volume": 2.9, "coin": "ETH", "Sold Amount": 1}, {"Collection name": "mfers", "volume": 2.7, "coin": "ETH", "Sold Amount": 3}, {"Collection name": "Gents Croquet Club", "volume": 2.6, "coin": "ETH", "Sold Amount": 1}, {"Collection name": "ArcheWorld_FandomCard", "volume": 19650.0, "coin": "KLAY", "Sold Amount": 8}, {"Collection name": "World of Women", "volume": 2.3, "coin": "ETH", "Sold Amount": 2}, {"Collection name": "Saved Souls", "volume": 2.7, "coin": "ETH", "Sold Amount": 103}, {"Collection name": "BEANZ Official", "volume": 2.8, "coin": "ETH", "Sold Amount": 2}, {"Collection name": "Iron Paw Gang", "volume": 2.7, "coin": "ETH", "Sold Amount": 4}, {"Collection name": "Delabs Adventure Pass Official", "volume": 2.9, "coin": "ETH", "Sold Amount": 22}, {"Collection name": "a KID called BEAST", "volume": 2.0, "coin": "ETH", "Sold Amount": 2}, {"Collection name": "ParaVault", "volume": 1.8, "coin": "ETH", "Sold Amount": 7}, {"Collection name": "rektguy", "volume": 1.7, "coin": "ETH", "Sold Amount": 2}, {"Collection name": "BROZO", "volume": 1.6, "coin": "ETH", "Sold Amount": 21}, {"Collection name": "Live Like A Cat -neko no youni ikiru-", "volume": 1.9, "coin": "ETH", "Sold Amount": 2}, {"Collection name": "SMS - Saishu Mirai Shoujo", "volume": 2.0, "coin": "ETH", "Sold Amount": 27}, {"Collection name": "Hedz by Matt Furie", "volume": 2.0, "coin": "ETH", "Sold Amount": 1}, {"Collection name": "The Plooshies", "volume": 2.3, "coin": "ETH", "Sold Amount": 19}, {"Collection name": "RTFKT Animus Egg \ud83e\udd5a", "volume": 1.4, "coin": "ETH", "Sold Amount": 3}, {"Collection name": "LlamaPix Genesis", "volume": 1.4, "coin": "ETH", "Sold Amount": 289}, {"Collection name": "GMX Blueberry Club", "volume": 1.4, "coin": "ETH", "Sold Amount": 5}, {"Collection name": "CryptoDickbutts", "volume": 1.3, "coin": "ETH", "Sold Amount": 1}, {"Collection name": "Pixelady Maker", "volume": 1.4, "coin": "ETH", "Sold Amount": 9}, {"Collection name": "Just a Basic Profile Picture", "volume": 1.4, "coin": "ETH", "Sold Amount": 70}, {"Collection name": "Homage by Rafa\u00ebl Rozendaal", "volume": 1.5, "coin": "ETH", "Sold Amount": 1}, {"Collection name": "Lens Protocol Profiles", "volume": 1.4, "coin": "ETH", "Sold Amount": 14}, {"Collection name": "0N1 Force", "volume": 1.6, "coin": "ETH", "Sold Amount": 2}, {"Collection name": "LuppyclubOfficial", "volume": 1.3, "coin": "ETH", "Sold Amount": 2}, {"Collection name": "My Curio Cards", "volume": 1.2, "coin": "ETH", "Sold Amount": 1}, {"Collection name": "SchizoPosters", "volume": 1.1, "coin": "ETH", "Sold Amount": 4}, {"Collection name": "Emblem Vault Legacy", "volume": 1.1, "coin": "ETH", "Sold Amount": 3}, {"Collection name": "Kubz", "volume": 1.2, "coin": "ETH", "Sold Amount": 1}, {"Collection name": "Creepz by OVERLORD", "volume": 1.3, "coin": "ETH", "Sold Amount": 1}, {"Collection name": "8lements", "volume": 1.3, "coin": "ETH", "Sold Amount": 52}, {"Collection name": "Unordinals", "volume": 1.3, "coin": "ETH", "Sold Amount": 3}, {"Collection name": "DeBox Guardians Penguin", "volume": 1.0, "coin": "ETH", "Sold Amount": 1}, {"Collection name": "WAFUKU GEN", "volume": 0.99, "coin": "ETH", "Sold Amount": 15}, {"Collection name": "Friendship Bracelets by Alexis Andr\u00e9", "volume": 0.95, "coin": "ETH", "Sold Amount": 4}, {"Collection name": "DenDekaDen Spirit Key Avatars", "volume": 0.8, "coin": "ETH", "Sold Amount": 7}, {"Collection name": "The Real Vision Collective", "volume": 0.8, "coin": "ETH", "Sold Amount": 1}, {"Collection name": "League of Kingdoms Drago [Ethereum]", "volume": 0.98, "coin": "ETH", "Sold Amount": 6}, {"Collection name": "Sidus Items", "volume": 1.0, "coin": "ETH", "Sold Amount": 1}, {"Collection name": "IlluminatiNFT by Truth Labs", "volume": 1.0, "coin": "ETH", "Sold Amount": 4}, {"Collection name": "The Memes by 6529", "volume": 1.0, "coin": "ETH", "Sold Amount": 1}, {"Collection name": "Dogemigos", "volume": 0.78, "coin": "ETH", "Sold Amount": 75}, {"Collection name": "YuliOriginGenOne", "volume": 4.5, "coin": "BNB", "Sold Amount": 5}, {"Collection name": "Obits Official", "volume": 0.76, "coin": "ETH", "Sold Amount": 2}, {"Collection name": "Shrapnel Operators Collection", "volume": 0.75, "coin": "ETH", "Sold Amount": 2}, {"Collection name": "bluutopiaNFT", "volume": 0.74, "coin": "ETH", "Sold Amount": 15}, {"Collection name": "THE ROALAND", "volume": 6001.8, "coin": "KLAY", "Sold Amount": 4}, {"Collection name": "Genesis Dimensional Stones", "volume": 0.77, "coin": "ETH", "Sold Amount": 1}, {"Collection name": "Mutant Hounds", "volume": 0.78, "coin": "ETH", "Sold Amount": 1}, {"Collection name": "Tunney Munney", "volume": 0.72, "coin": "ETH", "Sold Amount": 5}, {"Collection name": "MetaVixens", "volume": 0.65, "coin": "ETH", "Sold Amount": 1}, {"Collection name": "Gh0stly Gh0sts", "volume": 0.6, "coin": "ETH", "Sold Amount": 3}, {"Collection name": "Wilder Beasts: Wolf", "volume": 0.55, "coin": "ETH", "Sold Amount": 1}, {"Collection name": "Realm Hunter: Key Of Salvation", "volume": 0.51, "coin": "ETH", "Sold Amount": 14}, {"Collection name": "ArcheWorld_Land", "volume": 4510.6, "coin": "KLAY", "Sold Amount": 2}, {"Collection name": "RTFKT Clone X Forging SZN 1 (PRE-FORGE) \u2692\ufe0f", "volume": 0.61, "coin": "ETH", "Sold Amount": 2}, {"Collection name": "Pixelmon Evolution Serum", "volume": 0.66, "coin": "ETH", "Sold Amount": 1}, {"Collection name": "Chimpers", "volume": 0.73, "coin": "ETH", "Sold Amount": 1}, {"Collection name": "Dead Avatars", "volume": 0.51, "coin": "ETH", "Sold Amount": 1}, {"Collection name": "Midnight Society Founders Access Pass", "volume": 0.45, "coin": "ETH", "Sold Amount": 1}, {"Collection name": "Umuco's ART", "volume": 0.44, "coin": "ETH", "Sold Amount": 4}, {"Collection name": "10KTF Gucci Grail", "volume": 0.43, "coin": "ETH", "Sold Amount": 1}, {"Collection name": "Rug Radio - Genesis NFT", "volume": 0.47, "coin": "ETH", "Sold Amount": 2}]