[{"Collection name": "CLONE X - X TAKASHI MURAKAMI", "volume": 13.8, "coin": "ETH", "Sold Amount": 4}, {"Collection name": "Neo Tokyo Citizens", "volume": 7.5, "coin": "ETH", "Sold Amount": 1}, {"Collection name": "Opepen Edition", "volume": 4.6, "coin": "ETH", "Sold Amount": 11}, {"Collection name": "Consortium Key", "volume": 3.7, "coin": "ETH", "Sold Amount": 1}, {"Collection name": "Valhalla", "volume": 3.1, "coin": "ETH", "Sold Amount": 4}, {"Collection name": "ASM Brains", "volume": 3.0, "coin": "ETH", "Sold Amount": 28}, {"Collection name": "Checks - VV Edition", "volume": 4.4, "coin": "ETH", "Sold Amount": 7}, {"Collection name": "PROOF Collective", "volume": 6.0, "coin": "ETH", "Sold Amount": 1}, {"Collection name": "TOPIA Worlds", "volume": 5.3, "coin": "ETH", "Sold Amount": 3}, {"Collection name": "Blitmap", "volume": 7.0, "coin": "ETH", "Sold Amount": 1}, {"Collection name": "The Captainz", "volume": 9.9, "coin": "ETH", "Sold Amount": 1}, {"Collection name": "Redacted Remilio Babies", "volume": 8.0, "coin": "ETH", "Sold Amount": 5}, {"Collection name": "Kanpai Pandas", "volume": 11.0, "coin": "ETH", "Sold Amount": 10}, {"Collection name": "Meebits", "volume": 22.8, "coin": "ETH", "Sold Amount": 9}, {"Collection name": "RarePass: Genesis", "volume": 14.5, "coin": "ETH", "Sold Amount": 1}, {"Collection name": "Pudgy Penguins", "volume": 14.5, "coin": "ETH", "Sold Amount": 3}, {"Collection name": "0N1 Force", "volume": 20.7, "coin": "ETH", "Sold Amount": 15}, {"Collection name": "Moonbirds", "volume": 35.3, "coin": "ETH", "Sold Amount": 17}, {"Collection name": "HV-MTL", "volume": 26.8, "coin": "ETH", "Sold Amount": 12}, {"Collection name": "Mutant Ape Yacht Club", "volume": 60.7, "coin": "ETH", "Sold Amount": 6}]